<?xml version="1.0" encoding="UTF-8" ?>
<!DOCTYPE struts PUBLIC
    "-//Apache Software Foundation//DTD Struts Configuration 2.1.7//EN"
    "http://struts.apache.org/dtds/struts-2.1.7.dtd">

<struts>
	<constant name="struts.objectFactory" value="spring" />
	<constant name="struts.action.extension" value="do" />

	<package name="userlogin" namespace="" extends="struts-default">
		<!-- 配置拦截器 -->
		<!--interceptors>
			<interceptor name="myInterceptor" class="myInterceptor"></interceptor>
			<interceptor-stack name="myDefult">
				<interceptor-ref name="myInterceptor"></interceptor-ref>
				<interceptor-ref name="defaultStack"></interceptor-ref>
			</interceptor-stack>
		</interceptors-->
		
		<action name="userAction" class="userAction" method="fetchUserList">
			<result name="fetchUserList">/fetchUserList.jsp</result>
		</action>
	</package>

</struts>